yt_subs_migrate/__main__.py
yt_subs_migrate/cli.py
yt_subs_migrate/subscriptions.py
yt_subs_migrate-1.0.1.dist-info/LICENSE
yt_subs_migrate-1.0.1.dist-info/METADATA
yt_subs_migrate-1.0.1.dist-info/WHEEL
yt_subs_migrate-1.0.1.dist-info/entry_points.txt
yt_subs_migrate-1.0.1.dist-info/top_level.txt
yt_subs_migrate-1.0.1.dist-info/RECORD
