Metadata-Version: 2.1
Name: yt-subs-migrate
Version: 1.0.1
Summary: Migrate YouTube subscriptions from one account to another
Author-email: Trần Nam Tuấn <tuantran1632001@gmail.com>
License: GNU GENERAL PUBLIC LICENSE
Project-URL: Homepage, https://gitlab.com/TheBill2001/yt-subs-migrate
Project-URL: Bug Tracker, https://gitlab.com/TheBill2001/yt-subs-migrate/-/issues
Classifier: Programming Language :: Python :: 3.11
Classifier: License :: OSI Approved :: GNU General Public License v3 (GPLv3)
Classifier: Operating System :: OS Independent
Requires-Python: >=3.11
License-File: LICENSE
Requires-Dist: google-auth-oauthlib (>=1.0.0)
Requires-Dist: google-api-python-client (>=2.89.0)
Requires-Dist: tqdm
